coaxial_wakesleepmanager/__init__.py
coaxial_wakesleepmanager/__main__.py
coaxial_wakesleepmanager/cli.py
coaxial_wakesleepmanager/device_manager.py
coaxial_wakesleepmanager/network_scanner.py
coaxial_wakesleepmanager/uninstall.py
coaxial_wakesleepmanager-0.1.0.dist-info/METADATA
coaxial_wakesleepmanager-0.1.0.dist-info/WHEEL
coaxial_wakesleepmanager-0.1.0.dist-info/entry_points.txt
coaxial_wakesleepmanager-0.1.0.dist-info/top_level.txt
coaxial_wakesleepmanager-0.1.0.dist-info/RECORD
