Metadata-Version: 2.4
Name: coaxial-wakesleepmanager
Version: 0.1.0
Summary: A cross-platform tool to manage wake and sleep states of network devices
Author: Petter
License: MIT
Classifier: Programming Language :: Python :: 3
Classifier: License :: OSI Approved :: MIT License
Classifier: Operating System :: OS Independent
Requires-Python: >=3.6
Requires-Dist: wakeonlan>=2.1.0
Requires-Dist: paramiko>=3.3.1
Requires-Dist: click>=8.1.7
Requires-Dist: rich>=13.7.0
Requires-Dist: python-dotenv>=1.0.0
Requires-Dist: ping3>=4.0.4
Dynamic: requires-python
